Metadata-Version: 1.0
Name: ssj
Version: 2.0.0
Summary: Servidor ou gestor de dados em JSON com criptografia Fernet.
Home-page: UNKNOWN
Author: Jonathan N. Nagel
Author-email: jinnascimento81@gmail.com
License: MIT
Keywords: ssj
Platform: UNKNOWN
